WADLibrary/Driver.py
WADLibrary/Keywords.py
WADLibrary/Sessions.py
WADLibrary/__init__.py
WADLibrary/common/__init__.py
WADLibrary/common/errors.py
WADLibrary/common/execute.py
WADLibrary/common/keys.py
common/__init__.py
common/errors.py
common/execute.py
common/keys.py
robotframework_wadlibrary-20.6.4.dist-info/LICENSE
robotframework_wadlibrary-20.6.4.dist-info/METADATA
robotframework_wadlibrary-20.6.4.dist-info/WHEEL
robotframework_wadlibrary-20.6.4.dist-info/top_level.txt
robotframework_wadlibrary-20.6.4.dist-info/RECORD
