Metadata-Version: 2.1
Name: robotframework-wadlibrary
Version: 20.6.4
Summary: WADLibrary
Home-page: https://github.com/Adwisit/WADLibrary
Author: Elias Hachichou, Adwisit
Author-email: elias.hachichou@adwisit.se
License: UNKNOWN
Platform: UNKNOWN
Classifier: Programming Language :: Python :: 3
Classifier: License :: OSI Approved :: MIT License
Classifier: Operating System :: OS Independent
Requires-Dist: robotframework
Requires-Dist: requests
Requires-Dist: psutil
